dblp.py
awesome_dblp-1.0.dist-info/LICENSE
awesome_dblp-1.0.dist-info/METADATA
awesome_dblp-1.0.dist-info/WHEEL
awesome_dblp-1.0.dist-info/top_level.txt
awesome_dblp-1.0.dist-info/RECORD
